bintexttools/__init__.py
bintexttools/bin2text.py
bintexttools/text2bin.py
bintexttools/bintextcommon/BinTextCommon.py
bintexttools/bintextcommon/__init__.py
bintexttools/bintexthelper/Bin2TextConverter.py
bintexttools/bintexthelper/BinText.py
bintexttools/bintexthelper/Text2BinConverter.py
bintexttools/bintexthelper/TextFormat.py
bintexttools/bintexthelper/__init__.py
bintexttools-0.1.dist-info/LICENSE
bintexttools-0.1.dist-info/METADATA
bintexttools-0.1.dist-info/WHEEL
bintexttools-0.1.dist-info/entry_points.txt
bintexttools-0.1.dist-info/top_level.txt
bintexttools-0.1.dist-info/RECORD
