Metadata-Version: 2.1
Name: bintexttools
Version: 0.1
Summary: Tools for Binary and Text data.
Home-page: https://www.linkedin.com/in/marcin-zelek/
Author: Marcin Zelek
Author-email: marcin.zelek@gmail.com
License: MIT
Keywords: binary ascii text hex base64 convert tools
Platform: UNKNOWN
